{
  "username": "anton_sunrise",
  "start": "12 Oct 2015",
  "first": "653461144808620033",
  "post": false,
  "tweets": [
    {
      "created_at": "Mon Oct 12 06:45:55 +0000 2015",
      "id": 653461575752413200,
      "id_str": "653461575752413184",
      "text": "А для затравки, вот вам статья почему проекты фейлят и кто в этом виноват 6/6: http://t.co/5OrRwC0A9u",
      "source": "<a href=\"http://twitter.com\" rel=\"nofollow\">Twitter Web Client</a>",
      "truncated": false,
      "in_reply_to_status_id": null,
      "in_reply_to_status_id_str": null,
      "in_reply_to_user_id": null,
      "in_reply_to_user_id_str": null,
      "in_reply_to_screen_name": null,
      "user": {
        "id": 3302551618,
        "id_str": "3302551618"
      },
      "geo": null,
      "coordinates": null,
      "place": null,
      "contributors": null,
      "is_quote_status": false,
      "retweet_count": 0,
      "favorite_count": 0,
      "entities": {
        "hashtags": [],
        "symbols": [],
        "user_mentions": [],
        "urls": [
          {
            "url": "http://t.co/5OrRwC0A9u",
            "expanded_url": "http://bit.ly/1N7xjZV",
            "display_url": "bit.ly/1N7xjZV",
            "indices": [
              79,
              101
            ]
          }
        ]
      },
      "favorited": false,
      "retweeted": false,
      "possibly_sensitive": false,
      "lang": "ru"
    },
    {
      "created_at": "Mon Oct 12 06:45:35 +0000 2015",
      "id": 653461492935827500,
      "id_str": "653461492935827457",
      "text": "и о том куда податься разработчику. У меня будет много материалов на английском, потому что про PM по-русски пишут мало ((( 5/6",
      "source": "<a href=\"http://twitter.com\" rel=\"nofollow\">Twitter Web Client</a>",
      "truncated": false,
      "in_reply_to_status_id": null,
      "in_reply_to_status_id_str": null,
      "in_reply_to_user_id": null,
      "in_reply_to_user_id_str": null,
      "in_reply_to_screen_name": null,
      "user": {
        "id": 3302551618,
        "id_str": "3302551618"
      },
      "geo": null,
      "coordinates": null,
      "place": null,
      "contributors": null,
      "is_quote_status": false,
      "retweet_count": 0,
      "favorite_count": 0,
      "entities": {
        "hashtags": [],
        "symbols": [],
        "user_mentions": [],
        "urls": []
      },
      "favorited": false,
      "retweeted": false,
      "lang": "ru"
    },
    {
      "created_at": "Mon Oct 12 06:45:18 +0000 2015",
      "id": 653461422987444200,
      "id_str": "653461422987444224",
      "text": "Планирую поговорить с вами о том как и почему живут проекты, о том чего же от вас все-таки хотят менеджеры/заказчики и немного о карьере 4/6",
      "source": "<a href=\"http://twitter.com\" rel=\"nofollow\">Twitter Web Client</a>",
      "truncated": false,
      "in_reply_to_status_id": null,
      "in_reply_to_status_id_str": null,
      "in_reply_to_user_id": null,
      "in_reply_to_user_id_str": null,
      "in_reply_to_screen_name": null,
      "user": {
        "id": 3302551618,
        "id_str": "3302551618"
      },
      "geo": null,
      "coordinates": null,
      "place": null,
      "contributors": null,
      "is_quote_status": false,
      "retweet_count": 0,
      "favorite_count": 0,
      "entities": {
        "hashtags": [],
        "symbols": [],
        "user_mentions": [],
        "urls": []
      },
      "favorited": false,
      "retweeted": false,
      "lang": "ru"
    },
    {
      "created_at": "Mon Oct 12 06:44:54 +0000 2015",
      "id": 653461322563256300,
      "id_str": "653461322563256320",
      "text": "Последний год я живу/работаю в Европе, но команды у меня распределенные, в том числе и в бывшем СССР. 3/6",
      "source": "<a href=\"http://twitter.com\" rel=\"nofollow\">Twitter Web Client</a>",
      "truncated": false,
      "in_reply_to_status_id": null,
      "in_reply_to_status_id_str": null,
      "in_reply_to_user_id": null,
      "in_reply_to_user_id_str": null,
      "in_reply_to_screen_name": null,
      "user": {
        "id": 3302551618,
        "id_str": "3302551618"
      },
      "geo": null,
      "coordinates": null,
      "place": null,
      "contributors": null,
      "is_quote_status": false,
      "retweet_count": 0,
      "favorite_count": 0,
      "entities": {
        "hashtags": [],
        "symbols": [],
        "user_mentions": [],
        "urls": []
      },
      "favorited": false,
      "retweeted": false,
      "lang": "ru"
    },
    {
      "created_at": "Mon Oct 12 06:44:35 +0000 2015",
      "id": 653461240736534500,
      "id_str": "653461240736534528",
      "text": "Я занимаюсь управлением продуктами и проектами, в основном в области финансов, хотя немного удалось зацепить инфобез и облака. 2/6",
      "source": "<a href=\"http://twitter.com\" rel=\"nofollow\">Twitter Web Client</a>",
      "truncated": false,
      "in_reply_to_status_id": null,
      "in_reply_to_status_id_str": null,
      "in_reply_to_user_id": null,
      "in_reply_to_user_id_str": null,
      "in_reply_to_screen_name": null,
      "user": {
        "id": 3302551618,
        "id_str": "3302551618"
      },
      "geo": null,
      "coordinates": null,
      "place": null,
      "contributors": null,
      "is_quote_status": false,
      "retweet_count": 0,
      "favorite_count": 0,
      "entities": {
        "hashtags": [],
        "symbols": [],
        "user_mentions": [],
        "urls": []
      },
      "favorited": false,
      "retweeted": false,
      "lang": "ru"
    },
    {
      "created_at": "Mon Oct 12 06:44:12 +0000 2015",
      "id": 653461144808620000,
      "id_str": "653461144808620033",
      "text": "Привет всем, на этой неделе с вами буду я, представитель темной стороны силы (менеджеров) @anton_sunrise )) 1/6",
      "source": "<a href=\"http://twitter.com\" rel=\"nofollow\">Twitter Web Client</a>",
      "truncated": false,
      "in_reply_to_status_id": null,
      "in_reply_to_status_id_str": null,
      "in_reply_to_user_id": null,
      "in_reply_to_user_id_str": null,
      "in_reply_to_screen_name": null,
      "user": {
        "id": 3302551618,
        "id_str": "3302551618"
      },
      "geo": null,
      "coordinates": null,
      "place": null,
      "contributors": null,
      "is_quote_status": false,
      "retweet_count": 0,
      "favorite_count": 0,
      "entities": {
        "hashtags": [],
        "symbols": [],
        "user_mentions": [
          {
            "screen_name": "anton_sunrise",
            "name": "Anton Marchenko",
            "id": 114712818,
            "id_str": "114712818",
            "indices": [
              90,
              104
            ]
          }
        ],
        "urls": []
      },
      "favorited": false,
      "retweeted": false,
      "lang": "ru"
    }
  ]
}
