{
  "mentions": [
    {
      "created_at": "Mon Feb 01 09:16:51 +0000 2016",
      "id": 694087001285513200,
      "id_str": "694087001285513221",
      "text": "@backendsecret Поставь свой ник в профиль.",
      "source": "<a href=\"https://about.twitter.com/products/tweetdeck\" rel=\"nofollow\">TweetDeck</a>",
      "truncated": false,
      "in_reply_to_status_id": 694086287498809300,
      "in_reply_to_status_id_str": "694086287498809344",
      "in_reply_to_user_id": 3302551618,
      "in_reply_to_user_id_str": "3302551618",
      "in_reply_to_screen_name": "backendsecret",
      "user": {
        "id": 53938072,
        "id_str": "53938072"
      },
      "geo": null,
      "coordinates": null,
      "place": null,
      "contributors": null,
      "is_quote_status": false,
      "retweet_count": 0,
      "favorite_count": 0,
      "entities": {
        "hashtags": [],
        "symbols": [],
        "user_mentions": [
          {
            "screen_name": "backendsecret",
            "name": "Разработчик бэкенда",
            "id": 3302551618,
            "id_str": "3302551618",
            "indices": [
              0,
              14
            ]
          }
        ],
        "urls": []
      },
      "favorited": false,
      "retweeted": false,
      "lang": "ru"
    },
    {
      "created_at": "Mon Feb 01 09:18:05 +0000 2016",
      "id": 694087312863555600,
      "id_str": "694087312863555584",
      "text": "@backendsecret о, давай: кто возвращает 200 вместо 4xx и 5xx, тот...?",
      "source": "<a href=\"http://twitter.com\" rel=\"nofollow\">Twitter Web Client</a>",
      "truncated": false,
      "in_reply_to_status_id": 694086287498809300,
      "in_reply_to_status_id_str": "694086287498809344",
      "in_reply_to_user_id": 3302551618,
      "in_reply_to_user_id_str": "3302551618",
      "in_reply_to_screen_name": "backendsecret",
      "user": {
        "id": 88193411,
        "id_str": "88193411"
      },
      "geo": null,
      "coordinates": null,
      "place": null,
      "contributors": null,
      "is_quote_status": false,
      "retweet_count": 1,
      "favorite_count": 1,
      "entities": {
        "hashtags": [],
        "symbols": [],
        "user_mentions": [
          {
            "screen_name": "backendsecret",
            "name": "Разработчик бэкенда",
            "id": 3302551618,
            "id_str": "3302551618",
            "indices": [
              0,
              14
            ]
          }
        ],
        "urls": []
      },
      "favorited": false,
      "retweeted": true,
      "lang": "ru"
    },
    {
      "created_at": "Mon Feb 01 09:20:18 +0000 2016",
      "id": 694087868608860200,
      "id_str": "694087868608860160",
      "text": "@backendsecret где можно почитать про бестпрактисы по структуре REST API",
      "source": "<a href=\"http://twitter.com\" rel=\"nofollow\">Twitter Web Client</a>",
      "truncated": false,
      "in_reply_to_status_id": 694086287498809300,
      "in_reply_to_status_id_str": "694086287498809344",
      "in_reply_to_user_id": 3302551618,
      "in_reply_to_user_id_str": "3302551618",
      "in_reply_to_screen_name": "backendsecret",
      "user": {
        "id": 4819835579,
        "id_str": "4819835579"
      },
      "geo": null,
      "coordinates": null,
      "place": null,
      "contributors": null,
      "is_quote_status": false,
      "retweet_count": 1,
      "favorite_count": 0,
      "entities": {
        "hashtags": [],
        "symbols": [],
        "user_mentions": [
          {
            "screen_name": "backendsecret",
            "name": "Разработчик бэкенда",
            "id": 3302551618,
            "id_str": "3302551618",
            "indices": [
              0,
              14
            ]
          }
        ],
        "urls": []
      },
      "favorited": false,
      "retweeted": true,
      "lang": "ru"
    },
    {
      "created_at": "Mon Feb 01 09:20:28 +0000 2016",
      "id": 694087911239729200,
      "id_str": "694087911239729152",
      "text": "@backendsecret @retran Доброе утро! Добавил в статистику: https://t.co/nKli1LCOWX",
      "source": "<a href=\"http://twitter.com\" rel=\"nofollow\">Twitter Web Client</a>",
      "truncated": false,
      "in_reply_to_status_id": 694085450831695900,
      "in_reply_to_status_id_str": "694085450831695872",
      "in_reply_to_user_id": 3302551618,
      "in_reply_to_user_id_str": "3302551618",
      "in_reply_to_screen_name": "backendsecret",
      "user": {
        "id": 81103006,
        "id_str": "81103006"
      },
      "geo": null,
      "coordinates": null,
      "place": null,
      "contributors": null,
      "is_quote_status": false,
      "retweet_count": 0,
      "favorite_count": 0,
      "entities": {
        "hashtags": [],
        "symbols": [],
        "user_mentions": [
          {
            "screen_name": "backendsecret",
            "name": "Разработчик бэкенда",
            "id": 3302551618,
            "id_str": "3302551618",
            "indices": [
              0,
              14
            ]
          },
          {
            "screen_name": "retran",
            "name": "Andrew Vasilyev",
            "id": 66444133,
            "id_str": "66444133",
            "indices": [
              15,
              22
            ]
          }
        ],
        "urls": [
          {
            "url": "https://t.co/nKli1LCOWX",
            "expanded_url": "http://backendsecret.ru/stats/",
            "display_url": "backendsecret.ru/stats/",
            "indices": [
              58,
              81
            ]
          }
        ]
      },
      "favorited": false,
      "retweeted": false,
      "possibly_sensitive": false,
      "lang": "ru"
    },
    {
      "created_at": "Mon Feb 01 09:22:03 +0000 2016",
      "id": 694088310592028700,
      "id_str": "694088310592028672",
      "text": "@gvsmirnov @backendsecret jsonRpc?",
      "source": "<a href=\"https://about.twitter.com/products/tweetdeck\" rel=\"nofollow\">TweetDeck</a>",
      "truncated": false,
      "in_reply_to_status_id": 694087312863555600,
      "in_reply_to_status_id_str": "694087312863555584",
      "in_reply_to_user_id": 88193411,
      "in_reply_to_user_id_str": "88193411",
      "in_reply_to_screen_name": "gvsmirnov",
      "user": {
        "id": 524575848,
        "id_str": "524575848"
      },
      "geo": null,
      "coordinates": null,
      "place": null,
      "contributors": null,
      "is_quote_status": false,
      "retweet_count": 1,
      "favorite_count": 0,
      "entities": {
        "hashtags": [],
        "symbols": [],
        "user_mentions": [
          {
            "screen_name": "gvsmirnov",
            "name": "Gleb Smirnov",
            "id": 88193411,
            "id_str": "88193411",
            "indices": [
              0,
              10
            ]
          },
          {
            "screen_name": "backendsecret",
            "name": "Разработчик бэкенда",
            "id": 3302551618,
            "id_str": "3302551618",
            "indices": [
              11,
              25
            ]
          }
        ],
        "urls": []
      },
      "favorited": false,
      "retweeted": true,
      "lang": "cs"
    },
    {
      "created_at": "Mon Feb 01 09:27:18 +0000 2016",
      "id": 694089631747412000,
      "id_str": "694089631747411968",
      "text": "@backendsecret подскажи единственно верный способ аутентификации в JSON API",
      "source": "<a href=\"http://twitter.com/download/iphone\" rel=\"nofollow\">Twitter for iPhone</a>",
      "truncated": false,
      "in_reply_to_status_id": 694085974524072000,
      "in_reply_to_status_id_str": "694085974524071936",
      "in_reply_to_user_id": 3302551618,
      "in_reply_to_user_id_str": "3302551618",
      "in_reply_to_screen_name": "backendsecret",
      "user": {
        "id": 53391978,
        "id_str": "53391978"
      },
      "geo": null,
      "coordinates": null,
      "place": null,
      "contributors": null,
      "is_quote_status": false,
      "retweet_count": 0,
      "favorite_count": 0,
      "entities": {
        "hashtags": [],
        "symbols": [],
        "user_mentions": [
          {
            "screen_name": "backendsecret",
            "name": "Разработчик бэкенда",
            "id": 3302551618,
            "id_str": "3302551618",
            "indices": [
              0,
              14
            ]
          }
        ],
        "urls": []
      },
      "favorited": false,
      "retweeted": false,
      "lang": "bg"
    },
    {
      "created_at": "Mon Feb 01 09:30:52 +0000 2016",
      "id": 694090528548323300,
      "id_str": "694090528548323328",
      "text": "@backendsecret каким инструментом для создания документации по API пользуетесь?",
      "source": "<a href=\"https://about.twitter.com/products/tweetdeck\" rel=\"nofollow\">TweetDeck</a>",
      "truncated": false,
      "in_reply_to_status_id": 694089944797704200,
      "in_reply_to_status_id_str": "694089944797704192",
      "in_reply_to_user_id": 3302551618,
      "in_reply_to_user_id_str": "3302551618",
      "in_reply_to_screen_name": "backendsecret",
      "user": {
        "id": 1316599309,
        "id_str": "1316599309"
      },
      "geo": null,
      "coordinates": null,
      "place": null,
      "contributors": null,
      "is_quote_status": false,
      "retweet_count": 0,
      "favorite_count": 0,
      "entities": {
        "hashtags": [],
        "symbols": [],
        "user_mentions": [
          {
            "screen_name": "backendsecret",
            "name": "Разработчик бэкенда",
            "id": 3302551618,
            "id_str": "3302551618",
            "indices": [
              0,
              14
            ]
          }
        ],
        "urls": []
      },
      "favorited": false,
      "retweeted": false,
      "lang": "ru"
    },
    {
      "created_at": "Mon Feb 01 09:32:49 +0000 2016",
      "id": 694091022335369200,
      "id_str": "694091022335369217",
      "text": "@backendsecret есть опыт внедрения HATEOAS? что думаешь?",
      "source": "<a href=\"http://twitter.com\" rel=\"nofollow\">Twitter Web Client</a>",
      "truncated": false,
      "in_reply_to_status_id": 694086287498809300,
      "in_reply_to_status_id_str": "694086287498809344",
      "in_reply_to_user_id": 3302551618,
      "in_reply_to_user_id_str": "3302551618",
      "in_reply_to_screen_name": "backendsecret",
      "user": {
        "id": 42017834,
        "id_str": "42017834"
      },
      "geo": null,
      "coordinates": null,
      "place": {
        "id": "084d0d0155787e9d",
        "url": "https://api.twitter.com/1.1/geo/id/084d0d0155787e9d.json",
        "place_type": "country",
        "name": "Ukraine",
        "full_name": "Ukraine",
        "country_code": "UA",
        "country": "Ukraina",
        "contained_within": [],
        "bounding_box": {
          "type": "Polygon",
          "coordinates": [
            [
              [
                22.1357201,
                44.386383
              ],
              [
                40.227172,
                44.386383
              ],
              [
                40.227172,
                52.379475
              ],
              [
                22.1357201,
                52.379475
              ]
            ]
          ]
        },
        "attributes": {}
      },
      "contributors": null,
      "is_quote_status": false,
      "retweet_count": 0,
      "favorite_count": 0,
      "entities": {
        "hashtags": [],
        "symbols": [],
        "user_mentions": [
          {
            "screen_name": "backendsecret",
            "name": "Разработчик бэкенда",
            "id": 3302551618,
            "id_str": "3302551618",
            "indices": [
              0,
              14
            ]
          }
        ],
        "urls": []
      },
      "favorited": false,
      "retweeted": false,
      "lang": "ru"
    },
    {
      "created_at": "Mon Feb 01 09:34:03 +0000 2016",
      "id": 694091329865916400,
      "id_str": "694091329865916416",
      "text": "@backendsecret \nhttps://t.co/wAeMpmGk4z просто, четко, однозначно. https://t.co/U6zyC0USNc критика REST от Yandex",
      "source": "<a href=\"https://about.twitter.com/products/tweetdeck\" rel=\"nofollow\">TweetDeck</a>",
      "truncated": false,
      "in_reply_to_status_id": 694089944797704200,
      "in_reply_to_status_id_str": "694089944797704192",
      "in_reply_to_user_id": 3302551618,
      "in_reply_to_user_id_str": "3302551618",
      "in_reply_to_screen_name": "backendsecret",
      "user": {
        "id": 524575848,
        "id_str": "524575848"
      },
      "geo": null,
      "coordinates": null,
      "place": null,
      "contributors": null,
      "is_quote_status": false,
      "retweet_count": 0,
      "favorite_count": 0,
      "entities": {
        "hashtags": [],
        "symbols": [],
        "user_mentions": [
          {
            "screen_name": "backendsecret",
            "name": "Разработчик бэкенда",
            "id": 3302551618,
            "id_str": "3302551618",
            "indices": [
              0,
              14
            ]
          }
        ],
        "urls": [
          {
            "url": "https://t.co/wAeMpmGk4z",
            "expanded_url": "http://www.jsonrpc.org/specification",
            "display_url": "jsonrpc.org/specification",
            "indices": [
              16,
              39
            ]
          },
          {
            "url": "https://t.co/U6zyC0USNc",
            "expanded_url": "https://youtu.be/2atObx1D0hc",
            "display_url": "youtu.be/2atObx1D0hc",
            "indices": [
              67,
              90
            ]
          }
        ]
      },
      "favorited": false,
      "retweeted": false,
      "possibly_sensitive": false,
      "lang": "ru"
    },
    {
      "created_at": "Mon Feb 01 09:36:59 +0000 2016",
      "id": 694092070944899100,
      "id_str": "694092070944899072",
      "text": "\"@vassilevsky: @backendsecret подскажи единственно верный способ аутентификации в JSON API\" OAuth 2.0",
      "source": "<a href=\"https://mobile.twitter.com\" rel=\"nofollow\">Mobile Web (M5)</a>",
      "truncated": false,
      "in_reply_to_status_id": null,
      "in_reply_to_status_id_str": null,
      "in_reply_to_user_id": null,
      "in_reply_to_user_id_str": null,
      "in_reply_to_screen_name": null,
      "user": {
        "id": 3302551618,
        "id_str": "3302551618"
      },
      "geo": null,
      "coordinates": null,
      "place": null,
      "contributors": null,
      "is_quote_status": false,
      "retweet_count": 0,
      "favorite_count": 1,
      "entities": {
        "hashtags": [],
        "symbols": [],
        "user_mentions": [
          {
            "screen_name": "vassilevsky",
            "name": "White Russian",
            "id": 53391978,
            "id_str": "53391978",
            "indices": [
              1,
              13
            ]
          },
          {
            "screen_name": "backendsecret",
            "name": "Разработчик бэкенда",
            "id": 3302551618,
            "id_str": "3302551618",
            "indices": [
              15,
              29
            ]
          }
        ],
        "urls": []
      },
      "favorited": false,
      "retweeted": false,
      "lang": "bg"
    },
    {
      "created_at": "Mon Feb 01 09:38:09 +0000 2016",
      "id": 694092363610849300,
      "id_str": "694092363610849280",
      "text": "\"@atnartur: @backendsecret каким инструментом для создания документации по API пользуетесь?\" https://t.co/jHCbNrObFo",
      "source": "<a href=\"https://mobile.twitter.com\" rel=\"nofollow\">Mobile Web (M5)</a>",
      "truncated": false,
      "in_reply_to_status_id": null,
      "in_reply_to_status_id_str": null,
      "in_reply_to_user_id": null,
      "in_reply_to_user_id_str": null,
      "in_reply_to_screen_name": null,
      "user": {
        "id": 3302551618,
        "id_str": "3302551618"
      },
      "geo": null,
      "coordinates": null,
      "place": null,
      "contributors": null,
      "is_quote_status": false,
      "retweet_count": 0,
      "favorite_count": 1,
      "entities": {
        "hashtags": [],
        "symbols": [],
        "user_mentions": [
          {
            "screen_name": "atnartur",
            "name": "atnartur",
            "id": 1316599309,
            "id_str": "1316599309",
            "indices": [
              1,
              10
            ]
          },
          {
            "screen_name": "backendsecret",
            "name": "Разработчик бэкенда",
            "id": 3302551618,
            "id_str": "3302551618",
            "indices": [
              12,
              26
            ]
          }
        ],
        "urls": [
          {
            "url": "https://t.co/jHCbNrObFo",
            "expanded_url": "https://visualstudiomagazine.com/articles/2014/09/01/web-api-documentation-tools.aspx?m=1",
            "display_url": "visualstudiomagazine.com/articles/2014/…",
            "indices": [
              93,
              116
            ]
          }
        ]
      },
      "favorited": false,
      "retweeted": false,
      "possibly_sensitive": false,
      "lang": "ru"
    },
    {
      "created_at": "Mon Feb 01 09:38:46 +0000 2016",
      "id": 694092516392595500,
      "id_str": "694092516392595456",
      "text": "@backendsecret а что лучший?",
      "source": "<a href=\"http://twitter.com\" rel=\"nofollow\">Twitter Web Client</a>",
      "truncated": false,
      "in_reply_to_status_id": 694089944797704200,
      "in_reply_to_status_id_str": "694089944797704192",
      "in_reply_to_user_id": 3302551618,
      "in_reply_to_user_id_str": "3302551618",
      "in_reply_to_screen_name": "backendsecret",
      "user": {
        "id": 219867940,
        "id_str": "219867940"
      },
      "geo": null,
      "coordinates": null,
      "place": null,
      "contributors": null,
      "is_quote_status": false,
      "retweet_count": 0,
      "favorite_count": 0,
      "entities": {
        "hashtags": [],
        "symbols": [],
        "user_mentions": [
          {
            "screen_name": "backendsecret",
            "name": "Разработчик бэкенда",
            "id": 3302551618,
            "id_str": "3302551618",
            "indices": [
              0,
              14
            ]
          }
        ],
        "urls": []
      },
      "favorited": false,
      "retweeted": false,
      "lang": "ru"
    },
    {
      "created_at": "Mon Feb 01 09:41:04 +0000 2016",
      "id": 694093097668579300,
      "id_str": "694093097668579328",
      "text": "@OdinYury @backendsecret https://t.co/v14ROidywC",
      "source": "<a href=\"http://twitter.com/download/android\" rel=\"nofollow\">Twitter for Android</a>",
      "truncated": false,
      "in_reply_to_status_id": 694087868608860200,
      "in_reply_to_status_id_str": "694087868608860160",
      "in_reply_to_user_id": 4819835579,
      "in_reply_to_user_id_str": "4819835579",
      "in_reply_to_screen_name": "OdinYury",
      "user": {
        "id": 125115421,
        "id_str": "125115421"
      },
      "geo": null,
      "coordinates": null,
      "place": null,
      "contributors": null,
      "is_quote_status": false,
      "retweet_count": 1,
      "favorite_count": 1,
      "entities": {
        "hashtags": [],
        "symbols": [],
        "user_mentions": [
          {
            "screen_name": "OdinYury",
            "name": "Yury Odin",
            "id": 4819835579,
            "id_str": "4819835579",
            "indices": [
              0,
              9
            ]
          },
          {
            "screen_name": "backendsecret",
            "name": "Разработчик бэкенда",
            "id": 3302551618,
            "id_str": "3302551618",
            "indices": [
              10,
              24
            ]
          }
        ],
        "urls": [
          {
            "url": "https://t.co/v14ROidywC",
            "expanded_url": "http://shop.oreilly.com/product/mobile/0636920021575.do",
            "display_url": "shop.oreilly.com/product/mobile…",
            "indices": [
              25,
              48
            ]
          }
        ]
      },
      "favorited": false,
      "retweeted": true,
      "possibly_sensitive": false,
      "lang": "und"
    },
    {
      "created_at": "Mon Feb 01 09:52:18 +0000 2016",
      "id": 694095923060809700,
      "id_str": "694095923060809728",
      "text": "@backendsecret ооо, нормуль!\nЗадень в т.ч. проблемы реализаций в реальных системах, а-ля ожидание/реальность",
      "source": "<a href=\"http://twitter.com\" rel=\"nofollow\">Twitter Web Client</a>",
      "truncated": false,
      "in_reply_to_status_id": 694086287498809300,
      "in_reply_to_status_id_str": "694086287498809344",
      "in_reply_to_user_id": 3302551618,
      "in_reply_to_user_id_str": "3302551618",
      "in_reply_to_screen_name": "backendsecret",
      "user": {
        "id": 115212561,
        "id_str": "115212561"
      },
      "geo": null,
      "coordinates": null,
      "place": null,
      "contributors": null,
      "is_quote_status": false,
      "retweet_count": 0,
      "favorite_count": 0,
      "entities": {
        "hashtags": [],
        "symbols": [],
        "user_mentions": [
          {
            "screen_name": "backendsecret",
            "name": "Разработчик бэкенда",
            "id": 3302551618,
            "id_str": "3302551618",
            "indices": [
              0,
              14
            ]
          }
        ],
        "urls": []
      },
      "favorited": false,
      "retweeted": false,
      "lang": "ru"
    },
    {
      "created_at": "Mon Feb 01 10:07:05 +0000 2016",
      "id": 694099644092158000,
      "id_str": "694099644092157952",
      "text": ".@OdinYury Всем рекомендую эту статью https://t.co/oJ1QhHzZkS @backendsecret",
      "source": "<a href=\"http://twitter.com\" rel=\"nofollow\">Twitter Web Client</a>",
      "truncated": false,
      "in_reply_to_status_id": 694087868608860200,
      "in_reply_to_status_id_str": "694087868608860160",
      "in_reply_to_user_id": 4819835579,
      "in_reply_to_user_id_str": "4819835579",
      "in_reply_to_screen_name": "OdinYury",
      "user": {
        "id": 115212561,
        "id_str": "115212561"
      },
      "geo": null,
      "coordinates": null,
      "place": null,
      "contributors": null,
      "is_quote_status": false,
      "retweet_count": 1,
      "favorite_count": 4,
      "entities": {
        "hashtags": [],
        "symbols": [],
        "user_mentions": [
          {
            "screen_name": "OdinYury",
            "name": "Yury Odin",
            "id": 4819835579,
            "id_str": "4819835579",
            "indices": [
              1,
              10
            ]
          },
          {
            "screen_name": "backendsecret",
            "name": "Разработчик бэкенда",
            "id": 3302551618,
            "id_str": "3302551618",
            "indices": [
              62,
              76
            ]
          }
        ],
        "urls": [
          {
            "url": "https://t.co/oJ1QhHzZkS",
            "expanded_url": "http://blog.2partsmagic.com/restful-uri-design/",
            "display_url": "blog.2partsmagic.com/restful-uri-de…",
            "indices": [
              38,
              61
            ]
          }
        ]
      },
      "favorited": false,
      "retweeted": true,
      "possibly_sensitive": false,
      "lang": "ru"
    },
    {
      "created_at": "Mon Feb 01 10:09:51 +0000 2016",
      "id": 694100338102657000,
      "id_str": "694100338102657024",
      "text": "@backendsecret protobuf давно уже сосет",
      "source": "<a href=\"http://twitter.com\" rel=\"nofollow\">Twitter Web Client</a>",
      "truncated": false,
      "in_reply_to_status_id": 694100170057842700,
      "in_reply_to_status_id_str": "694100170057842689",
      "in_reply_to_user_id": 3302551618,
      "in_reply_to_user_id_str": "3302551618",
      "in_reply_to_screen_name": "backendsecret",
      "user": {
        "id": 127573172,
        "id_str": "127573172"
      },
      "geo": null,
      "coordinates": null,
      "place": null,
      "contributors": null,
      "is_quote_status": false,
      "retweet_count": 0,
      "favorite_count": 0,
      "entities": {
        "hashtags": [],
        "symbols": [],
        "user_mentions": [
          {
            "screen_name": "backendsecret",
            "name": "Разработчик бэкенда",
            "id": 3302551618,
            "id_str": "3302551618",
            "indices": [
              0,
              14
            ]
          }
        ],
        "urls": []
      },
      "favorited": false,
      "retweeted": false,
      "lang": "und"
    },
    {
      "created_at": "Mon Feb 01 10:11:36 +0000 2016",
      "id": 694100778689130500,
      "id_str": "694100778689130496",
      "text": "Каждый понедельник - это не только начало новой недели, но и новые авторы-\"андерхуды\" :) @abroadunderhood @backendsecret @jsunderhood",
      "source": "<a href=\"http://itunes.apple.com/us/app/twitter/id409789998?mt=12\" rel=\"nofollow\">Twitter for Mac</a>",
      "truncated": false,
      "in_reply_to_status_id": null,
      "in_reply_to_status_id_str": null,
      "in_reply_to_user_id": null,
      "in_reply_to_user_id_str": null,
      "in_reply_to_screen_name": null,
      "user": {
        "id": 243507698,
        "id_str": "243507698"
      },
      "geo": null,
      "coordinates": null,
      "place": null,
      "contributors": null,
      "is_quote_status": false,
      "retweet_count": 0,
      "favorite_count": 0,
      "entities": {
        "hashtags": [],
        "symbols": [],
        "user_mentions": [
          {
            "screen_name": "abroadunderhood",
            "name": "Эброд Андэрхуд",
            "id": 3955812173,
            "id_str": "3955812173",
            "indices": [
              89,
              105
            ]
          },
          {
            "screen_name": "backendsecret",
            "name": "Разработчик бэкенда",
            "id": 3302551618,
            "id_str": "3302551618",
            "indices": [
              106,
              120
            ]
          },
          {
            "screen_name": "jsunderhood",
            "name": "Разработчик",
            "id": 3014054307,
            "id_str": "3014054307",
            "indices": [
              121,
              133
            ]
          }
        ],
        "urls": []
      },
      "favorited": false,
      "retweeted": false,
      "lang": "ru"
    },
    {
      "created_at": "Mon Feb 01 10:19:41 +0000 2016",
      "id": 694102816198168600,
      "id_str": "694102816198168576",
      "text": "@backendsecret если у вас xml - не забудьте не использовать его больше никогда.",
      "source": "<a href=\"http://github.com/remhume/Hermelin/\" rel=\"nofollow\">Hermelin</a>",
      "truncated": false,
      "in_reply_to_status_id": 694102473544462300,
      "in_reply_to_status_id_str": "694102473544462336",
      "in_reply_to_user_id": 3302551618,
      "in_reply_to_user_id_str": "3302551618",
      "in_reply_to_screen_name": "backendsecret",
      "user": {
        "id": 53967484,
        "id_str": "53967484"
      },
      "geo": null,
      "coordinates": null,
      "place": null,
      "contributors": null,
      "is_quote_status": false,
      "retweet_count": 0,
      "favorite_count": 0,
      "entities": {
        "hashtags": [],
        "symbols": [],
        "user_mentions": [
          {
            "screen_name": "backendsecret",
            "name": "Разработчик бэкенда",
            "id": 3302551618,
            "id_str": "3302551618",
            "indices": [
              0,
              14
            ]
          }
        ],
        "urls": []
      },
      "favorited": false,
      "retweeted": false,
      "lang": "ru"
    }
  ]
}
