{
  "mentions": [
    {
      "created_at": "Mon Dec 10 06:44:01 +0000 2018",
      "id": 1072019085033136100,
      "id_str": "1072019085033136128",
      "text": "@backendsecret а представиться?",
      "truncated": false,
      "entities": {
        "hashtags": [],
        "symbols": [],
        "user_mentions": [
          {
            "screen_name": "backendsecret",
            "name": "Разработчик backend'а",
            "id": 3302551618,
            "id_str": "3302551618",
            "indices": [
              0,
              14
            ]
          }
        ],
        "urls": []
      },
      "source": "<a href=\"http://twitter.com\" rel=\"nofollow\">Twitter Web Client</a>",
      "in_reply_to_status_id": 1072018012473974800,
      "in_reply_to_status_id_str": "1072018012473974784",
      "in_reply_to_user_id": 3302551618,
      "in_reply_to_user_id_str": "3302551618",
      "in_reply_to_screen_name": "backendsecret",
      "user": {
        "id": 574420152,
        "id_str": "574420152"
      },
      "geo": null,
      "coordinates": null,
      "place": null,
      "contributors": null,
      "is_quote_status": false,
      "retweet_count": 0,
      "favorite_count": 0,
      "favorited": false,
      "retweeted": false,
      "lang": "ru"
    },
    {
      "created_at": "Mon Dec 10 06:46:59 +0000 2018",
      "id": 1072019830268747800,
      "id_str": "1072019830268747776",
      "text": "@backendsecret Совет - пропускайте твиты через сервисы проверки орфографии",
      "truncated": false,
      "entities": {
        "hashtags": [],
        "symbols": [],
        "user_mentions": [
          {
            "screen_name": "backendsecret",
            "name": "Разработчик backend'а",
            "id": 3302551618,
            "id_str": "3302551618",
            "indices": [
              0,
              14
            ]
          }
        ],
        "urls": []
      },
      "source": "<a href=\"http://twitter.com/download/android\" rel=\"nofollow\">Twitter for Android</a>",
      "in_reply_to_status_id": 1072018012473974800,
      "in_reply_to_status_id_str": "1072018012473974784",
      "in_reply_to_user_id": 3302551618,
      "in_reply_to_user_id_str": "3302551618",
      "in_reply_to_screen_name": "backendsecret",
      "user": {
        "id": 9310862,
        "id_str": "9310862"
      },
      "geo": null,
      "coordinates": null,
      "place": null,
      "contributors": null,
      "is_quote_status": false,
      "retweet_count": 0,
      "favorite_count": 0,
      "favorited": false,
      "retweeted": false,
      "lang": "ru"
    },
    {
      "created_at": "Mon Dec 10 07:06:43 +0000 2018",
      "id": 1072024795620016100,
      "id_str": "1072024795620016129",
      "text": "@backendsecret Backend уже не тот 🙊",
      "truncated": false,
      "entities": {
        "hashtags": [],
        "symbols": [],
        "user_mentions": [
          {
            "screen_name": "backendsecret",
            "name": "Разработчик backend'а",
            "id": 3302551618,
            "id_str": "3302551618",
            "indices": [
              0,
              14
            ]
          }
        ],
        "urls": []
      },
      "source": "<a href=\"http://twitter.com/download/android\" rel=\"nofollow\">Twitter for Android</a>",
      "in_reply_to_status_id": 1072018012473974800,
      "in_reply_to_status_id_str": "1072018012473974784",
      "in_reply_to_user_id": 3302551618,
      "in_reply_to_user_id_str": "3302551618",
      "in_reply_to_screen_name": "backendsecret",
      "user": {
        "id": 18577007,
        "id_str": "18577007"
      },
      "geo": null,
      "coordinates": null,
      "place": null,
      "contributors": null,
      "is_quote_status": false,
      "retweet_count": 0,
      "favorite_count": 0,
      "favorited": false,
      "retweeted": false,
      "lang": "und"
    },
    {
      "created_at": "Mon Dec 10 07:17:57 +0000 2018",
      "id": 1072027625634390000,
      "id_str": "1072027625634390016",
      "text": "@backendsecret Вы по образованию психолог? Что заканчивали?",
      "truncated": false,
      "entities": {
        "hashtags": [],
        "symbols": [],
        "user_mentions": [
          {
            "screen_name": "backendsecret",
            "name": "Разработчик backend'а",
            "id": 3302551618,
            "id_str": "3302551618",
            "indices": [
              0,
              14
            ]
          }
        ],
        "urls": []
      },
      "source": "<a href=\"http://twitter.com\" rel=\"nofollow\">Twitter Web Client</a>",
      "in_reply_to_status_id": 1072021343363838000,
      "in_reply_to_status_id_str": "1072021343363837953",
      "in_reply_to_user_id": 3302551618,
      "in_reply_to_user_id_str": "3302551618",
      "in_reply_to_screen_name": "backendsecret",
      "user": {
        "id": 71539732,
        "id_str": "71539732"
      },
      "geo": null,
      "coordinates": null,
      "place": null,
      "contributors": null,
      "is_quote_status": false,
      "retweet_count": 0,
      "favorite_count": 0,
      "favorited": false,
      "retweeted": false,
      "lang": "ru"
    },
    {
      "created_at": "Mon Dec 10 07:23:05 +0000 2018",
      "id": 1072028913705074700,
      "id_str": "1072028913705074689",
      "text": "@backendsecret не хватает элементов, типа клиента - ну формально он не задачу ставит, а хотелки выражает",
      "truncated": false,
      "entities": {
        "hashtags": [],
        "symbols": [],
        "user_mentions": [
          {
            "screen_name": "backendsecret",
            "name": "Разработчик backend'а",
            "id": 3302551618,
            "id_str": "3302551618",
            "indices": [
              0,
              14
            ]
          }
        ],
        "urls": []
      },
      "source": "<a href=\"http://twitter.com\" rel=\"nofollow\">Twitter Web Client</a>",
      "in_reply_to_status_id": 1072026482392948700,
      "in_reply_to_status_id_str": "1072026482392948736",
      "in_reply_to_user_id": 3302551618,
      "in_reply_to_user_id_str": "3302551618",
      "in_reply_to_screen_name": "backendsecret",
      "user": {
        "id": 963022516108382200,
        "id_str": "963022516108382209"
      },
      "geo": null,
      "coordinates": null,
      "place": null,
      "contributors": null,
      "is_quote_status": false,
      "retweet_count": 0,
      "favorite_count": 0,
      "favorited": false,
      "retweeted": false,
      "lang": "ru"
    },
    {
      "created_at": "Mon Dec 10 07:26:01 +0000 2018",
      "id": 1072029654347849700,
      "id_str": "1072029654347849728",
      "text": "На этой неделе @backendsecret обещает быть необычным",
      "truncated": false,
      "entities": {
        "hashtags": [],
        "symbols": [],
        "user_mentions": [
          {
            "screen_name": "backendsecret",
            "name": "Разработчик backend'а",
            "id": 3302551618,
            "id_str": "3302551618",
            "indices": [
              15,
              29
            ]
          }
        ],
        "urls": []
      },
      "source": "<a href=\"http://twitter.com/download/iphone\" rel=\"nofollow\">Twitter for iPhone</a>",
      "in_reply_to_status_id": null,
      "in_reply_to_status_id_str": null,
      "in_reply_to_user_id": null,
      "in_reply_to_user_id_str": null,
      "in_reply_to_screen_name": null,
      "user": {
        "id": 192284876,
        "id_str": "192284876"
      },
      "geo": null,
      "coordinates": null,
      "place": null,
      "contributors": null,
      "is_quote_status": false,
      "retweet_count": 0,
      "favorite_count": 1,
      "favorited": false,
      "retweeted": false,
      "lang": "ru"
    },
    {
      "created_at": "Mon Dec 10 07:32:14 +0000 2018",
      "id": 1072031219209158700,
      "id_str": "1072031219209158658",
      "text": "@backendsecret Где пункт «я сам»?",
      "truncated": false,
      "entities": {
        "hashtags": [],
        "symbols": [],
        "user_mentions": [
          {
            "screen_name": "backendsecret",
            "name": "Разработчик backend'а",
            "id": 3302551618,
            "id_str": "3302551618",
            "indices": [
              0,
              14
            ]
          }
        ],
        "urls": []
      },
      "source": "<a href=\"http://twitter.com/download/android\" rel=\"nofollow\">Twitter for Android</a>",
      "in_reply_to_status_id": 1072026482392948700,
      "in_reply_to_status_id_str": "1072026482392948736",
      "in_reply_to_user_id": 3302551618,
      "in_reply_to_user_id_str": "3302551618",
      "in_reply_to_screen_name": "backendsecret",
      "user": {
        "id": 6918532,
        "id_str": "6918532"
      },
      "geo": null,
      "coordinates": null,
      "place": null,
      "contributors": null,
      "is_quote_status": false,
      "retweet_count": 0,
      "favorite_count": 1,
      "favorited": false,
      "retweeted": false,
      "lang": "ru"
    },
    {
      "created_at": "Mon Dec 10 07:33:25 +0000 2018",
      "id": 1072031517415796700,
      "id_str": "1072031517415796736",
      "text": "@GolerGkA @backendsecret Отвечай «команда». Это чуть более продвинутый вариант того же.",
      "truncated": false,
      "entities": {
        "hashtags": [],
        "symbols": [],
        "user_mentions": [
          {
            "screen_name": "GolerGkA",
            "name": "зануда, туповат",
            "id": 6918532,
            "id_str": "6918532",
            "indices": [
              0,
              9
            ]
          },
          {
            "screen_name": "backendsecret",
            "name": "Разработчик backend'а",
            "id": 3302551618,
            "id_str": "3302551618",
            "indices": [
              10,
              24
            ]
          }
        ],
        "urls": []
      },
      "source": "<a href=\"http://twitter.com/download/iphone\" rel=\"nofollow\">Twitter for iPhone</a>",
      "in_reply_to_status_id": 1072031219209158700,
      "in_reply_to_status_id_str": "1072031219209158658",
      "in_reply_to_user_id": 6918532,
      "in_reply_to_user_id_str": "6918532",
      "in_reply_to_screen_name": "GolerGkA",
      "user": {
        "id": 181550231,
        "id_str": "181550231"
      },
      "geo": null,
      "coordinates": null,
      "place": null,
      "contributors": null,
      "is_quote_status": false,
      "retweet_count": 0,
      "favorite_count": 1,
      "favorited": false,
      "retweeted": false,
      "lang": "ru"
    },
    {
      "created_at": "Mon Dec 10 08:09:01 +0000 2018",
      "id": 1072040475941589000,
      "id_str": "1072040475941588992",
      "text": "@backendsecret @alexanius ну у нас до сих пор считается минимум стыдно ходить к психологу и дальше. \"Ты что псих?\"",
      "truncated": false,
      "entities": {
        "hashtags": [],
        "symbols": [],
        "user_mentions": [
          {
            "screen_name": "backendsecret",
            "name": "Разработчик backend'а",
            "id": 3302551618,
            "id_str": "3302551618",
            "indices": [
              0,
              14
            ]
          },
          {
            "screen_name": "alexanius",
            "name": "Алексей Маркин",
            "id": 71539732,
            "id_str": "71539732",
            "indices": [
              15,
              25
            ]
          }
        ],
        "urls": []
      },
      "source": "<a href=\"http://twitter.com\" rel=\"nofollow\">Twitter Web Client</a>",
      "in_reply_to_status_id": 1072039365424107500,
      "in_reply_to_status_id_str": "1072039365424107520",
      "in_reply_to_user_id": 3302551618,
      "in_reply_to_user_id_str": "3302551618",
      "in_reply_to_screen_name": "backendsecret",
      "user": {
        "id": 81103006,
        "id_str": "81103006"
      },
      "geo": null,
      "coordinates": null,
      "place": null,
      "contributors": null,
      "is_quote_status": false,
      "retweet_count": 0,
      "favorite_count": 1,
      "favorited": false,
      "retweeted": false,
      "lang": "ru"
    },
    {
      "created_at": "Mon Dec 10 08:09:48 +0000 2018",
      "id": 1072040670754496500,
      "id_str": "1072040670754496512",
      "text": "@vittoriuz @_bravit @nikalaikina @backendsecret @Hixon101 «У меня тут сосед молоток, жалуется, что микроскопы и микрофоны плохо забивают»",
      "truncated": false,
      "entities": {
        "hashtags": [],
        "symbols": [],
        "user_mentions": [
          {
            "screen_name": "vittoriuz",
            "name": "Victor Zagorodny",
            "id": 77776543,
            "id_str": "77776543",
            "indices": [
              0,
              10
            ]
          },
          {
            "screen_name": "_bravit",
            "name": "Виталий Брагилевский",
            "id": 1337287994,
            "id_str": "1337287994",
            "indices": [
              11,
              19
            ]
          },
          {
            "screen_name": "nikalaikina",
            "name": "Вера и исключения",
            "id": 558604421,
            "id_str": "558604421",
            "indices": [
              20,
              32
            ]
          },
          {
            "screen_name": "backendsecret",
            "name": "Разработчик backend'а",
            "id": 3302551618,
            "id_str": "3302551618",
            "indices": [
              33,
              47
            ]
          },
          {
            "screen_name": "Hixon101",
            "name": "Denis",
            "id": 215293252,
            "id_str": "215293252",
            "indices": [
              48,
              57
            ]
          }
        ],
        "urls": []
      },
      "source": "<a href=\"http://twitter.com/download/iphone\" rel=\"nofollow\">Twitter for iPhone</a>",
      "in_reply_to_status_id": 1072007799259971600,
      "in_reply_to_status_id_str": "1072007799259971584",
      "in_reply_to_user_id": 77776543,
      "in_reply_to_user_id_str": "77776543",
      "in_reply_to_screen_name": "vittoriuz",
      "user": {
        "id": 191709625,
        "id_str": "191709625"
      },
      "geo": null,
      "coordinates": null,
      "place": null,
      "contributors": null,
      "is_quote_status": false,
      "retweet_count": 0,
      "favorite_count": 0,
      "favorited": false,
      "retweeted": false,
      "lang": "ru"
    },
    {
      "created_at": "Mon Dec 10 08:11:09 +0000 2018",
      "id": 1072041013294891000,
      "id_str": "1072041013294891009",
      "text": "@uncle_robot @backendsecret Ну не знаю. Тут очень сильно зависит от конкретных людей/круга общения (я с таким не ст… https://t.co/EX3PIuYnrt",
      "truncated": true,
      "entities": {
        "hashtags": [],
        "symbols": [],
        "user_mentions": [
          {
            "screen_name": "uncle_robot",
            "name": "🤖 Дядя 🄿обот 🤖",
            "id": 81103006,
            "id_str": "81103006",
            "indices": [
              0,
              12
            ]
          },
          {
            "screen_name": "backendsecret",
            "name": "Разработчик backend'а",
            "id": 3302551618,
            "id_str": "3302551618",
            "indices": [
              13,
              27
            ]
          }
        ],
        "urls": [
          {
            "url": "https://t.co/EX3PIuYnrt",
            "expanded_url": "https://twitter.com/i/web/status/1072041013294891009",
            "display_url": "twitter.com/i/web/status/1…",
            "indices": [
              117,
              140
            ]
          }
        ]
      },
      "source": "<a href=\"http://twitter.com\" rel=\"nofollow\">Twitter Web Client</a>",
      "in_reply_to_status_id": 1072040475941589000,
      "in_reply_to_status_id_str": "1072040475941588992",
      "in_reply_to_user_id": 81103006,
      "in_reply_to_user_id_str": "81103006",
      "in_reply_to_screen_name": "uncle_robot",
      "user": {
        "id": 71539732,
        "id_str": "71539732"
      },
      "geo": null,
      "coordinates": null,
      "place": null,
      "contributors": null,
      "is_quote_status": false,
      "retweet_count": 0,
      "favorite_count": 0,
      "favorited": false,
      "retweeted": false,
      "lang": "ru"
    },
    {
      "created_at": "Mon Dec 10 08:12:06 +0000 2018",
      "id": 1072041249752916000,
      "id_str": "1072041249752915968",
      "text": "@alexanius @backendsecret Почему хорошо не посещать психологов (и дальше)?",
      "truncated": false,
      "entities": {
        "hashtags": [],
        "symbols": [],
        "user_mentions": [
          {
            "screen_name": "alexanius",
            "name": "Алексей Маркин",
            "id": 71539732,
            "id_str": "71539732",
            "indices": [
              0,
              10
            ]
          },
          {
            "screen_name": "backendsecret",
            "name": "Разработчик backend'а",
            "id": 3302551618,
            "id_str": "3302551618",
            "indices": [
              11,
              25
            ]
          }
        ],
        "urls": []
      },
      "source": "<a href=\"http://twitter.com\" rel=\"nofollow\">Twitter Web Client</a>",
      "in_reply_to_status_id": 1072041013294891000,
      "in_reply_to_status_id_str": "1072041013294891009",
      "in_reply_to_user_id": 71539732,
      "in_reply_to_user_id_str": "71539732",
      "in_reply_to_screen_name": "alexanius",
      "user": {
        "id": 81103006,
        "id_str": "81103006"
      },
      "geo": null,
      "coordinates": null,
      "place": null,
      "contributors": null,
      "is_quote_status": false,
      "retweet_count": 0,
      "favorite_count": 0,
      "favorited": false,
      "retweeted": false,
      "lang": "ru"
    },
    {
      "created_at": "Mon Dec 10 08:13:25 +0000 2018",
      "id": 1072041582994559000,
      "id_str": "1072041582994558976",
      "text": "@backendsecret На чём коробочку писать будем?",
      "truncated": false,
      "entities": {
        "hashtags": [],
        "symbols": [],
        "user_mentions": [
          {
            "screen_name": "backendsecret",
            "name": "Разработчик backend'а",
            "id": 3302551618,
            "id_str": "3302551618",
            "indices": [
              0,
              14
            ]
          }
        ],
        "urls": []
      },
      "source": "<a href=\"http://twitter.com/download/iphone\" rel=\"nofollow\">Twitter for iPhone</a>",
      "in_reply_to_status_id": 1072021343363838000,
      "in_reply_to_status_id_str": "1072021343363837953",
      "in_reply_to_user_id": 3302551618,
      "in_reply_to_user_id_str": "3302551618",
      "in_reply_to_screen_name": "backendsecret",
      "user": {
        "id": 191709625,
        "id_str": "191709625"
      },
      "geo": null,
      "coordinates": null,
      "place": null,
      "contributors": null,
      "is_quote_status": false,
      "retweet_count": 0,
      "favorite_count": 0,
      "favorited": false,
      "retweeted": false,
      "lang": "ru"
    },
    {
      "created_at": "Mon Dec 10 08:14:46 +0000 2018",
      "id": 1072041921466560500,
      "id_str": "1072041921466560512",
      "text": "@uncle_robot @backendsecret Я не говорил что хорошо не посещать :) Я сказал что плохо делать это так как на западе.… https://t.co/lKm9Frhj8p",
      "truncated": true,
      "entities": {
        "hashtags": [],
        "symbols": [],
        "user_mentions": [
          {
            "screen_name": "uncle_robot",
            "name": "🤖 Дядя 🄿обот 🤖",
            "id": 81103006,
            "id_str": "81103006",
            "indices": [
              0,
              12
            ]
          },
          {
            "screen_name": "backendsecret",
            "name": "Разработчик backend'а",
            "id": 3302551618,
            "id_str": "3302551618",
            "indices": [
              13,
              27
            ]
          }
        ],
        "urls": [
          {
            "url": "https://t.co/lKm9Frhj8p",
            "expanded_url": "https://twitter.com/i/web/status/1072041921466560512",
            "display_url": "twitter.com/i/web/status/1…",
            "indices": [
              117,
              140
            ]
          }
        ]
      },
      "source": "<a href=\"http://twitter.com\" rel=\"nofollow\">Twitter Web Client</a>",
      "in_reply_to_status_id": 1072041249752916000,
      "in_reply_to_status_id_str": "1072041249752915968",
      "in_reply_to_user_id": 81103006,
      "in_reply_to_user_id_str": "81103006",
      "in_reply_to_screen_name": "uncle_robot",
      "user": {
        "id": 71539732,
        "id_str": "71539732"
      },
      "geo": null,
      "coordinates": null,
      "place": null,
      "contributors": null,
      "is_quote_status": false,
      "retweet_count": 0,
      "favorite_count": 1,
      "favorited": false,
      "retweeted": false,
      "lang": "ru"
    },
    {
      "created_at": "Mon Dec 10 08:15:24 +0000 2018",
      "id": 1072042080833294300,
      "id_str": "1072042080833294337",
      "text": "@backendsecret @alexanius Да, у нас на группе говорят, что нет здоровых людей. Есть скрывающие проблемы :D",
      "truncated": false,
      "entities": {
        "hashtags": [],
        "symbols": [],
        "user_mentions": [
          {
            "screen_name": "backendsecret",
            "name": "Разработчик backend'а",
            "id": 3302551618,
            "id_str": "3302551618",
            "indices": [
              0,
              14
            ]
          },
          {
            "screen_name": "alexanius",
            "name": "Алексей Маркин",
            "id": 71539732,
            "id_str": "71539732",
            "indices": [
              15,
              25
            ]
          }
        ],
        "urls": []
      },
      "source": "<a href=\"http://twitter.com\" rel=\"nofollow\">Twitter Web Client</a>",
      "in_reply_to_status_id": 1072041816759906300,
      "in_reply_to_status_id_str": "1072041816759906304",
      "in_reply_to_user_id": 3302551618,
      "in_reply_to_user_id_str": "3302551618",
      "in_reply_to_screen_name": "backendsecret",
      "user": {
        "id": 81103006,
        "id_str": "81103006"
      },
      "geo": null,
      "coordinates": null,
      "place": null,
      "contributors": null,
      "is_quote_status": false,
      "retweet_count": 0,
      "favorite_count": 1,
      "favorited": true,
      "retweeted": false,
      "lang": "ru"
    },
    {
      "created_at": "Mon Dec 10 08:16:48 +0000 2018",
      "id": 1072042434174050300,
      "id_str": "1072042434174050304",
      "text": "@alexanius @backendsecret А... Извини, не правильно понял. Конечно будет нехватать общения если... https://t.co/XQmQMNw0DV",
      "truncated": false,
      "entities": {
        "hashtags": [],
        "symbols": [],
        "user_mentions": [
          {
            "screen_name": "alexanius",
            "name": "Алексей Маркин",
            "id": 71539732,
            "id_str": "71539732",
            "indices": [
              0,
              10
            ]
          },
          {
            "screen_name": "backendsecret",
            "name": "Разработчик backend'а",
            "id": 3302551618,
            "id_str": "3302551618",
            "indices": [
              11,
              25
            ]
          }
        ],
        "urls": [],
        "media": [
          {
            "id": 1072042417778516000,
            "id_str": "1072042417778515968",
            "indices": [
              99,
              122
            ],
            "media_url": "http://pbs.twimg.com/media/DuCo5ifW4AAAUbf.jpg",
            "media_url_https": "https://pbs.twimg.com/media/DuCo5ifW4AAAUbf.jpg",
            "url": "https://t.co/XQmQMNw0DV",
            "display_url": "pic.twitter.com/XQmQMNw0DV",
            "expanded_url": "https://twitter.com/uncle_robot/status/1072042434174050304/photo/1",
            "type": "photo",
            "sizes": {
              "medium": {
                "w": 640,
                "h": 366,
                "resize": "fit"
              },
              "large": {
                "w": 640,
                "h": 366,
                "resize": "fit"
              },
              "thumb": {
                "w": 150,
                "h": 150,
                "resize": "crop"
              },
              "small": {
                "w": 640,
                "h": 366,
                "resize": "fit"
              }
            }
          }
        ]
      },
      "extended_entities": {
        "media": [
          {
            "id": 1072042417778516000,
            "id_str": "1072042417778515968",
            "indices": [
              99,
              122
            ],
            "media_url": "http://pbs.twimg.com/media/DuCo5ifW4AAAUbf.jpg",
            "media_url_https": "https://pbs.twimg.com/media/DuCo5ifW4AAAUbf.jpg",
            "url": "https://t.co/XQmQMNw0DV",
            "display_url": "pic.twitter.com/XQmQMNw0DV",
            "expanded_url": "https://twitter.com/uncle_robot/status/1072042434174050304/photo/1",
            "type": "photo",
            "sizes": {
              "medium": {
                "w": 640,
                "h": 366,
                "resize": "fit"
              },
              "large": {
                "w": 640,
                "h": 366,
                "resize": "fit"
              },
              "thumb": {
                "w": 150,
                "h": 150,
                "resize": "crop"
              },
              "small": {
                "w": 640,
                "h": 366,
                "resize": "fit"
              }
            }
          }
        ]
      },
      "source": "<a href=\"http://twitter.com\" rel=\"nofollow\">Twitter Web Client</a>",
      "in_reply_to_status_id": 1072041921466560500,
      "in_reply_to_status_id_str": "1072041921466560512",
      "in_reply_to_user_id": 71539732,
      "in_reply_to_user_id_str": "71539732",
      "in_reply_to_screen_name": "alexanius",
      "user": {
        "id": 81103006,
        "id_str": "81103006"
      },
      "geo": null,
      "coordinates": null,
      "place": null,
      "contributors": null,
      "is_quote_status": false,
      "retweet_count": 0,
      "favorite_count": 0,
      "favorited": false,
      "retweeted": false,
      "possibly_sensitive": false,
      "lang": "ru"
    },
    {
      "created_at": "Mon Dec 10 08:18:05 +0000 2018",
      "id": 1072042755365486600,
      "id_str": "1072042755365486592",
      "text": "@uncle_robot @backendsecret о_О Особенно учитывая что психологи не могут ставить диагнозы. Возможно формулировка вс… https://t.co/BSFons4lpk",
      "truncated": true,
      "entities": {
        "hashtags": [],
        "symbols": [],
        "user_mentions": [
          {
            "screen_name": "uncle_robot",
            "name": "🤖 Дядя 🄿обот 🤖",
            "id": 81103006,
            "id_str": "81103006",
            "indices": [
              0,
              12
            ]
          },
          {
            "screen_name": "backendsecret",
            "name": "Разработчик backend'а",
            "id": 3302551618,
            "id_str": "3302551618",
            "indices": [
              13,
              27
            ]
          }
        ],
        "urls": [
          {
            "url": "https://t.co/BSFons4lpk",
            "expanded_url": "https://twitter.com/i/web/status/1072042755365486592",
            "display_url": "twitter.com/i/web/status/1…",
            "indices": [
              117,
              140
            ]
          }
        ]
      },
      "source": "<a href=\"http://twitter.com\" rel=\"nofollow\">Twitter Web Client</a>",
      "in_reply_to_status_id": 1072042080833294300,
      "in_reply_to_status_id_str": "1072042080833294337",
      "in_reply_to_user_id": 81103006,
      "in_reply_to_user_id_str": "81103006",
      "in_reply_to_screen_name": "uncle_robot",
      "user": {
        "id": 71539732,
        "id_str": "71539732"
      },
      "geo": null,
      "coordinates": null,
      "place": null,
      "contributors": null,
      "is_quote_status": false,
      "retweet_count": 0,
      "favorite_count": 1,
      "favorited": true,
      "retweeted": false,
      "lang": "ru"
    },
    {
      "created_at": "Mon Dec 10 08:19:39 +0000 2018",
      "id": 1072043152545144800,
      "id_str": "1072043152545144832",
      "text": "@backendsecret @Hixon101 Джаву скала потребляет без проблем. В обратную сторону хуже.",
      "truncated": false,
      "entities": {
        "hashtags": [],
        "symbols": [],
        "user_mentions": [
          {
            "screen_name": "backendsecret",
            "name": "Разработчик backend'а",
            "id": 3302551618,
            "id_str": "3302551618",
            "indices": [
              0,
              14
            ]
          },
          {
            "screen_name": "Hixon101",
            "name": "Denis",
            "id": 215293252,
            "id_str": "215293252",
            "indices": [
              15,
              24
            ]
          }
        ],
        "urls": []
      },
      "source": "<a href=\"http://twitter.com/download/iphone\" rel=\"nofollow\">Twitter for iPhone</a>",
      "in_reply_to_status_id": 1071826891571630100,
      "in_reply_to_status_id_str": "1071826891571630081",
      "in_reply_to_user_id": 3302551618,
      "in_reply_to_user_id_str": "3302551618",
      "in_reply_to_screen_name": "backendsecret",
      "user": {
        "id": 10634822,
        "id_str": "10634822"
      },
      "geo": null,
      "coordinates": null,
      "place": null,
      "contributors": null,
      "is_quote_status": false,
      "retweet_count": 0,
      "favorite_count": 1,
      "favorited": false,
      "retweeted": false,
      "lang": "ru"
    },
    {
      "created_at": "Mon Dec 10 08:28:24 +0000 2018",
      "id": 1072045352533012500,
      "id_str": "1072045352533012480",
      "text": "@alexanius @backendsecret Ну у нас группа \"следующего этапа\".",
      "truncated": false,
      "entities": {
        "hashtags": [],
        "symbols": [],
        "user_mentions": [
          {
            "screen_name": "alexanius",
            "name": "Алексей Маркин",
            "id": 71539732,
            "id_str": "71539732",
            "indices": [
              0,
              10
            ]
          },
          {
            "screen_name": "backendsecret",
            "name": "Разработчик backend'а",
            "id": 3302551618,
            "id_str": "3302551618",
            "indices": [
              11,
              25
            ]
          }
        ],
        "urls": []
      },
      "source": "<a href=\"http://twitter.com\" rel=\"nofollow\">Twitter Web Client</a>",
      "in_reply_to_status_id": 1072042755365486600,
      "in_reply_to_status_id_str": "1072042755365486592",
      "in_reply_to_user_id": 71539732,
      "in_reply_to_user_id_str": "71539732",
      "in_reply_to_screen_name": "alexanius",
      "user": {
        "id": 81103006,
        "id_str": "81103006"
      },
      "geo": null,
      "coordinates": null,
      "place": null,
      "contributors": null,
      "is_quote_status": false,
      "retweet_count": 0,
      "favorite_count": 0,
      "favorited": false,
      "retweeted": false,
      "lang": "ru"
    },
    {
      "created_at": "Mon Dec 10 08:28:29 +0000 2018",
      "id": 1072045376256073700,
      "id_str": "1072045376256073729",
      "text": "@backendsecret @Hixon101 у clojure должен быть нормальный интероп с жавой",
      "truncated": false,
      "entities": {
        "hashtags": [],
        "symbols": [],
        "user_mentions": [
          {
            "screen_name": "backendsecret",
            "name": "Разработчик backend'а",
            "id": 3302551618,
            "id_str": "3302551618",
            "indices": [
              0,
              14
            ]
          },
          {
            "screen_name": "Hixon101",
            "name": "Denis",
            "id": 215293252,
            "id_str": "215293252",
            "indices": [
              15,
              24
            ]
          }
        ],
        "urls": []
      },
      "source": "<a href=\"http://twitter.com/download/android\" rel=\"nofollow\">Twitter for Android</a>",
      "in_reply_to_status_id": 1071826891571630100,
      "in_reply_to_status_id_str": "1071826891571630081",
      "in_reply_to_user_id": 3302551618,
      "in_reply_to_user_id_str": "3302551618",
      "in_reply_to_screen_name": "backendsecret",
      "user": {
        "id": 750017037666230300,
        "id_str": "750017037666230272"
      },
      "geo": null,
      "coordinates": null,
      "place": null,
      "contributors": null,
      "is_quote_status": false,
      "retweet_count": 0,
      "favorite_count": 0,
      "favorited": false,
      "retweeted": false,
      "lang": "ru"
    },
    {
      "created_at": "Mon Dec 10 08:29:43 +0000 2018",
      "id": 1072045683144884200,
      "id_str": "1072045683144884224",
      "text": "@backendsecret такую коробочку вcе мечтают придумать, она бы сделала ненужными поликлиники в принципе",
      "truncated": false,
      "entities": {
        "hashtags": [],
        "symbols": [],
        "user_mentions": [
          {
            "screen_name": "backendsecret",
            "name": "Разработчик backend'а",
            "id": 3302551618,
            "id_str": "3302551618",
            "indices": [
              0,
              14
            ]
          }
        ],
        "urls": []
      },
      "source": "<a href=\"http://twitter.com\" rel=\"nofollow\">Twitter Web Client</a>",
      "in_reply_to_status_id": 1072021343363838000,
      "in_reply_to_status_id_str": "1072021343363837953",
      "in_reply_to_user_id": 3302551618,
      "in_reply_to_user_id_str": "3302551618",
      "in_reply_to_screen_name": "backendsecret",
      "user": {
        "id": 32959868,
        "id_str": "32959868"
      },
      "geo": null,
      "coordinates": null,
      "place": null,
      "contributors": null,
      "is_quote_status": false,
      "retweet_count": 0,
      "favorite_count": 1,
      "favorited": true,
      "retweeted": false,
      "lang": "ru"
    },
    {
      "created_at": "Mon Dec 10 08:39:17 +0000 2018",
      "id": 1072048091266760700,
      "id_str": "1072048091266760705",
      "text": "@backendsecret @alexanius Ну да, как наркотики, только действие другое.",
      "truncated": false,
      "entities": {
        "hashtags": [],
        "symbols": [],
        "user_mentions": [
          {
            "screen_name": "backendsecret",
            "name": "Разработчик backend'а",
            "id": 3302551618,
            "id_str": "3302551618",
            "indices": [
              0,
              14
            ]
          },
          {
            "screen_name": "alexanius",
            "name": "Алексей Маркин",
            "id": 71539732,
            "id_str": "71539732",
            "indices": [
              15,
              25
            ]
          }
        ],
        "urls": []
      },
      "source": "<a href=\"http://twitter.com\" rel=\"nofollow\">Twitter Web Client</a>",
      "in_reply_to_status_id": 1072047373864583200,
      "in_reply_to_status_id_str": "1072047373864583168",
      "in_reply_to_user_id": 3302551618,
      "in_reply_to_user_id_str": "3302551618",
      "in_reply_to_screen_name": "backendsecret",
      "user": {
        "id": 81103006,
        "id_str": "81103006"
      },
      "geo": null,
      "coordinates": null,
      "place": null,
      "contributors": null,
      "is_quote_status": false,
      "retweet_count": 0,
      "favorite_count": 0,
      "favorited": false,
      "retweeted": false,
      "lang": "ru"
    },
    {
      "created_at": "Mon Dec 10 08:50:10 +0000 2018",
      "id": 1072050831577497600,
      "id_str": "1072050831577497600",
      "text": "@backendsecret Сам",
      "truncated": false,
      "entities": {
        "hashtags": [],
        "symbols": [],
        "user_mentions": [
          {
            "screen_name": "backendsecret",
            "name": "Разработчик backend'а",
            "id": 3302551618,
            "id_str": "3302551618",
            "indices": [
              0,
              14
            ]
          }
        ],
        "urls": []
      },
      "source": "<a href=\"http://tapbots.com/tweetbot\" rel=\"nofollow\">Tweetbot for iΟS</a>",
      "in_reply_to_status_id": 1072026482392948700,
      "in_reply_to_status_id_str": "1072026482392948736",
      "in_reply_to_user_id": 3302551618,
      "in_reply_to_user_id_str": "3302551618",
      "in_reply_to_screen_name": "backendsecret",
      "user": {
        "id": 237366647,
        "id_str": "237366647"
      },
      "geo": null,
      "coordinates": null,
      "place": null,
      "contributors": null,
      "is_quote_status": false,
      "retweet_count": 0,
      "favorite_count": 0,
      "favorited": false,
      "retweeted": false,
      "lang": "ru"
    },
    {
      "created_at": "Mon Dec 10 09:00:44 +0000 2018",
      "id": 1072053491462479900,
      "id_str": "1072053491462479872",
      "text": "@backendsecret Отличный план, что тут сказать, будет интересно, имхо",
      "truncated": false,
      "entities": {
        "hashtags": [],
        "symbols": [],
        "user_mentions": [
          {
            "screen_name": "backendsecret",
            "name": "Разработчик backend'а",
            "id": 3302551618,
            "id_str": "3302551618",
            "indices": [
              0,
              14
            ]
          }
        ],
        "urls": []
      },
      "source": "<a href=\"http://twitter.com/download/iphone\" rel=\"nofollow\">Twitter for iPhone</a>",
      "in_reply_to_status_id": 1072040492664348700,
      "in_reply_to_status_id_str": "1072040492664348672",
      "in_reply_to_user_id": 3302551618,
      "in_reply_to_user_id_str": "3302551618",
      "in_reply_to_screen_name": "backendsecret",
      "user": {
        "id": 192284876,
        "id_str": "192284876"
      },
      "geo": null,
      "coordinates": null,
      "place": null,
      "contributors": null,
      "is_quote_status": false,
      "retweet_count": 0,
      "favorite_count": 0,
      "favorited": false,
      "retweeted": false,
      "lang": "ru"
    },
    {
      "created_at": "Mon Dec 10 09:02:48 +0000 2018",
      "id": 1072054011203858400,
      "id_str": "1072054011203858432",
      "text": "@backendsecret все чем занимаются в поликлиниках, это отправить обратно домой пить чай, потому что если чел сам дош… https://t.co/nUF0XGVG9R",
      "truncated": true,
      "entities": {
        "hashtags": [],
        "symbols": [],
        "user_mentions": [
          {
            "screen_name": "backendsecret",
            "name": "Разработчик backend'а",
            "id": 3302551618,
            "id_str": "3302551618",
            "indices": [
              0,
              14
            ]
          }
        ],
        "urls": [
          {
            "url": "https://t.co/nUF0XGVG9R",
            "expanded_url": "https://twitter.com/i/web/status/1072054011203858432",
            "display_url": "twitter.com/i/web/status/1…",
            "indices": [
              117,
              140
            ]
          }
        ]
      },
      "source": "<a href=\"http://twitter.com\" rel=\"nofollow\">Twitter Web Client</a>",
      "in_reply_to_status_id": 1072048581002059800,
      "in_reply_to_status_id_str": "1072048581002059776",
      "in_reply_to_user_id": 3302551618,
      "in_reply_to_user_id_str": "3302551618",
      "in_reply_to_screen_name": "backendsecret",
      "user": {
        "id": 32959868,
        "id_str": "32959868"
      },
      "geo": null,
      "coordinates": null,
      "place": null,
      "contributors": null,
      "is_quote_status": false,
      "retweet_count": 0,
      "favorite_count": 0,
      "favorited": false,
      "retweeted": false,
      "lang": "ru"
    }
  ]
}
